ksilorama/__init__.py
ksilorama/ansi.py
ksilorama/ansitowin32.py
ksilorama/initialise.py
ksilorama/win32.py
ksilorama/winterm.py
ksilorama/tests/__init__.py
ksilorama/tests/ansi_test.py
ksilorama/tests/ansitowin32_test.py
ksilorama/tests/initialise_test.py
ksilorama/tests/isatty_test.py
ksilorama/tests/utils.py
ksilorama/tests/winterm_test.py
ksilorama-0.4.11.dist-info/METADATA
ksilorama-0.4.11.dist-info/WHEEL
ksilorama-0.4.11.dist-info/licenses/LICENSE.txt
ksilorama-0.4.11.dist-info/RECORD
