Metadata-Version: 2.4
Name: ksilorama
Version: 0.4.11
Summary: Cross-platform colored terminal text.
Project-URL: Homepage, https://github.com/Kseen715/ksilorama
Author-email: Denis Korenev <korenevdn@gmail.com>, Jonathan Hartley <tartley@tartley.com>
License-Expression: BSD-3-Clause
License-File: LICENSE.txt
Keywords: ansi,color,colour,crossplatform,terminal,text,windows,xplatform
Classifier: Development Status :: 5 - Production/Stable
Classifier: Environment :: Console
Classifier: Intended Audience :: Developers
Classifier: License :: OSI Approved :: BSD License
Classifier: Operating System :: OS Independent
Classifier: Programming Language :: Python
Classifier: Programming Language :: Python :: 2
Classifier: Programming Language :: Python :: 2.7
Classifier: Programming Language :: Python :: 3
Classifier: Programming Language :: Python :: 3.7
Classifier: Programming Language :: Python :: 3.8
Classifier: Programming Language :: Python :: 3.9
Classifier: Programming Language :: Python :: 3.10
Classifier: Programming Language :: Python :: 3.11
Classifier: Programming Language :: Python :: 3.12
Classifier: Programming Language :: Python :: 3.13
Classifier: Programming Language :: Python :: Implementation :: CPython
Classifier: Programming Language :: Python :: Implementation :: PyPy
Classifier: Topic :: Terminals
Requires-Python: !=3.0.*,!=3.1.*,!=3.2.*,!=3.3.*,!=3.4.*,!=3.5.*,!=3.6.*,>=2.7
